{
  "NOTICE": "Not public API, DO NOT use this file",
  "release_pages": [
    {
      "index": 1,
      "etag": "\"deec7f2d80e81624f1b41d9444eb58b8779e49fe36bfaef3f5fcf2746a8d5ba8\"",
      "release_tags": [
        "qq_api-v1.2.1",
        "qq_api-v1.2.0",
        "qq_api-v1.1.1",
        "qq_api-v1.1.0",
        "qq_api-v1.0.0"
      ],
      "empty": false
    },
    {
      "index": 2,
      "etag": "\"1db6a3a21548bf6e068a9a9337e4151e9d1135718e089e7e62dc0509406337bf\"",
      "release_tags": [],
      "empty": true
    }
  ]
}